npstat/__init__.py
npstat/stats.py
npstat-0.6.dist-info/licenses/LICENSE
npstat-0.6.dist-info/METADATA
npstat-0.6.dist-info/WHEEL
npstat-0.6.dist-info/top_level.txt
npstat-0.6.dist-info/RECORD
